iotile_transport_websocket/__init__.py
iotile_transport_websocket/websocket_adapter.py
iotile_transport_websocket/websocket_implementation.py
iotile_transport_websocket/websocket_server.py
iotile_transport_websocket-3.2.0.dist-info/LICENSE.md
iotile_transport_websocket-3.2.0.dist-info/METADATA
iotile_transport_websocket-3.2.0.dist-info/WHEEL
iotile_transport_websocket-3.2.0.dist-info/entry_points.txt
iotile_transport_websocket-3.2.0.dist-info/top_level.txt
iotile_transport_websocket-3.2.0.dist-info/RECORD
